frontmatter_cli/__init__.py
frontmatter_cli/__main__.py
frontmatter_cli/cli.py
frontmatter_cli-2023.7.7.dist-info/LICENSE
frontmatter_cli-2023.7.7.dist-info/METADATA
frontmatter_cli-2023.7.7.dist-info/WHEEL
frontmatter_cli-2023.7.7.dist-info/entry_points.txt
frontmatter_cli-2023.7.7.dist-info/top_level.txt
frontmatter_cli-2023.7.7.dist-info/RECORD
