Metadata-Version: 2.1
Name: frontmatter-cli
Version: 2023.7.7
Summary: Frontmatter CLI tool to make working with frontmatter easier.
Author-email: Jeff Triplett <jeff.triplett@gmail.com>
License: BSD-3-Clause
Project-URL: Homepage, https://github.com/jefftriplett/frontmatter-cli
Project-URL: Issues, https://github.com/jefftriplett/frontmatter-cli/issues
Project-URL: Source, https://github.com/jefftriplett/frontmatter-cli
Keywords: frontmatter,frontmatter-cli
Classifier: Development Status :: 3 - Alpha
Classifier: Intended Audience :: Developers
Classifier: License :: OSI Approved :: BSD License
Classifier: Natural Language :: English
Classifier: Programming Language :: Python :: 3 :: Only
Classifier: Programming Language :: Python :: 3.8
Classifier: Programming Language :: Python :: 3.9
Classifier: Programming Language :: Python :: 3.10
Classifier: Programming Language :: Python :: 3.11
Requires-Python: >3.7
License-File: LICENSE
Requires-Dist: click
Requires-Dist: click-default-group
Requires-Dist: pydash
Requires-Dist: python-frontmatter
Provides-Extra: dev
Requires-Dist: build ; extra == 'dev'
Requires-Dist: bumpver ; extra == 'dev'
Requires-Dist: pip-tools ; extra == 'dev'
Requires-Dist: pre-commit ; extra == 'dev'
Requires-Dist: twine ; extra == 'dev'
